runtheshow/__init__.py
runtheshow/__version__.py
runtheshow/database.py
runtheshow/decorators.py
runtheshow/downloader.py
runtheshow/exceptions.py
runtheshow/fav.py
runtheshow/man.py
runtheshow/parser.py
runtheshow/show.py
runtheshow/utils.py
runtheshow-0.2.2.dist-info/DESCRIPTION.rst
runtheshow-0.2.2.dist-info/METADATA
runtheshow-0.2.2.dist-info/RECORD
runtheshow-0.2.2.dist-info/WHEEL
runtheshow-0.2.2.dist-info/entry_points.txt
runtheshow-0.2.2.dist-info/metadata.json
runtheshow-0.2.2.dist-info/top_level.txt
