Metadata-Version: 2.0
Name: runtheshow
Version: 0.2.2
Summary: Another Eztv API
Home-page: https://github.com/Germione/runtheshow
Author: Jerome Pradier
Author-email: jerome.pradier@gmail.com
License: MIT
Keywords: packaging setuptools development
Platform: UNKNOWN
Classifier: Development Status :: 4 - Beta
Classifier: Intended Audience :: Developers
Classifier: Topic :: Software Development :: Build Tools
Classifier: License :: OSI Approved :: MIT License
Classifier: Programming Language :: Python :: 2
Classifier: Programming Language :: Python :: 2.7
Classifier: Programming Language :: Python :: 3
Classifier: Programming Language :: Python :: 3.6
Requires-Dist: twine
Requires-Dist: keyring
Requires-Dist: requests
Requires-Dist: lxml
Requires-Dist: cssselect
